pyDeco/__init__.py
pyDeco/cli/__init__.py
pyDeco/cli/command.py
pyDeco/debug/__init__.py
pyDeco/debug/debug/inactive.py
pyDeco/debug/debug/redirect.py
pyDeco/debug/debug/stacktrace.py
pyDeco/fun/__init__.py
pyDeco/fun/epic_intro.py
pyDeco/fun/explode.py
pyDeco/info/__init__.py
pyDeco/info/memory.py
pyDeco/info/timeit.py
pyDeco/utils.py
python_deco-0.3.27.dist-info/LICENSE
python_deco-0.3.27.dist-info/METADATA
python_deco-0.3.27.dist-info/WHEEL
python_deco-0.3.27.dist-info/RECORD
