Metadata-Version: 2.1
Name: python-deco
Version: 0.3.27
Summary: 
Home-page: https://py-decorators.readthedocs.io/en/latest/index.html
License: LICENSE
Author: adrian
Author-email: tamkayeung.adrian@gmail.com
Requires-Python: >=3.6,<4.0
Classifier: License :: Other/Proprietary License
Classifier: Programming Language :: Python :: 3
Classifier: Programming Language :: Python :: 3.6
Classifier: Programming Language :: Python :: 3.7
Classifier: Programming Language :: Python :: 3.8
Classifier: Programming Language :: Python :: 3.9
Classifier: Programming Language :: Python :: 3.10
Classifier: Programming Language :: Python :: 3.11
Requires-Dist: PyYAML (>=6.0,<7.0)
Requires-Dist: pytest (>=7.2.1,<8.0.0)
Project-URL: Repository, https://github.com/kayeungadrian-tam/py_decorators
